literary/build_meta.py
literary_build-3.0.0.dist-info/LICENSE
literary_build-3.0.0.dist-info/METADATA
literary_build-3.0.0.dist-info/WHEEL
literary_build-3.0.0.dist-info/top_level.txt
literary_build-3.0.0.dist-info/RECORD
