Metadata-Version: 2.1
Name: literary-build
Version: 3.0.0
Summary: PEP 517 backend for literary package development with Jupyter
Home-page: https://github.com/agoose77/literary-build
Author: Angus Hollands
Author-email: goosey15@gmail.com
License: BSD-3-Clause
Project-URL: Bug Tracker, https://github.com/agoose77/literary-build/issues
Keywords: literate-programming,jupyter,notebooks,nbconvert,pep517,build,setuptools
Platform: Any
Classifier: Development Status :: 4 - Beta
Classifier: Intended Audience :: Developers
Classifier: Intended Audience :: Science/Research
Classifier: License :: OSI Approved :: BSD License
Classifier: Operating System :: OS Independent
Classifier: Programming Language :: Python
Classifier: Programming Language :: Python :: 3
Classifier: Programming Language :: Python :: 3 :: Only
Classifier: Programming Language :: Python :: 3.7
Classifier: Programming Language :: Python :: 3.8
Classifier: Programming Language :: Python :: 3.9
Requires-Python: >=3.7
License-File: LICENSE
Requires-Dist: literary (<4.0.0,>=3.0.0)
Requires-Dist: setuptools (>=46.4.0)
Requires-Dist: wheel
